todosync/__init__.py
todosync/__main__.py
todosync/database.py
todosync/todosync.py
todosync/source/__init__.py
todosync/source/bts.py
todosync/source/github.py
todosync/source/gitlab.py
todosync/source/test/__init__.py
todosync/source/test/bts_test.py
todosync/source/test/github_test.py
todosync/source/test/gitlab_test.py
todosync/test/__init__.py
todosync/test/database_test.py
todosync/test/todosync_test.py
todosync-0.4.0.dist-info/LICENSE
todosync-0.4.0.dist-info/METADATA
todosync-0.4.0.dist-info/WHEEL
todosync-0.4.0.dist-info/top_level.txt
todosync-0.4.0.dist-info/RECORD
