Metadata-Version: 2.1
Name: todosync
Version: 0.4.0
Summary: Synchronize issues & tasks from different sources into Todoist.
Home-page: https://github.com/creekorful/todosync
Author: Aloïs Micard
Author-email: alois@micard.lu
License: UNKNOWN
Project-URL: Bug Tracker, https://github.com/creekorful/todosync/issues
Platform: UNKNOWN
Classifier: Programming Language :: Python :: 3
Classifier: License :: OSI Approved :: GNU General Public License v3 (GPLv3)
Classifier: Operating System :: OS Independent
Requires-Python: >=3.9
License-File: LICENSE
